dirichletcal/__init__.py
dirichletcal/utils.py
dirichletcal/version.py
dirichletcal/calib/__init__.py
dirichletcal/calib/diagdirichlet.py
dirichletcal/calib/fixeddirichlet.py
dirichletcal/calib/fulldirichlet.py
dirichletcal/calib/gendirichlet.py
dirichletcal/calib/matrixscaling.py
dirichletcal/calib/multinomial.py
dirichletcal/calib/tempscaling.py
dirichletcal/calib/typeiidirichlet.py
dirichletcal/calib/vectorscaling.py
dirichletcal/tests/__init__.py
dirichletcal/tests/calib/__init__.py
dirichletcal/tests/calib/test_diagonaldirichlet.py
dirichletcal/tests/calib/test_fixeddirichlet.py
dirichletcal/tests/calib/test_fulldirichlet.py
dirichletcal/tests/calib/test_genfulldirichlet.py
dirichletcal/tests/calib/test_multinomial.py
dirichletcal/tests/calib/test_temperaturescaling.py
dirichletcal/tests/calib/test_vectorscaling.py
dirichletcal-0.1.dev1.dist-info/LICENSE.txt
dirichletcal-0.1.dev1.dist-info/METADATA
dirichletcal-0.1.dev1.dist-info/WHEEL
dirichletcal-0.1.dev1.dist-info/top_level.txt
dirichletcal-0.1.dev1.dist-info/RECORD
