Metadata-Version: 2.1
Name: dirichletcal
Version: 0.1.dev1
Summary: Python code for Dirichlet calibration
Home-page: https://github.com/dirichletcal/dirichlet_python
Author: Miquel Perello Nieto and Hao Song
Author-email: perello.nieto@gmail.com
License: UNKNOWN
Download-URL: https://github.com/dirichletcal/dirichlet_python/archive/0.1.dev1.tar.gz
Keywords: classifier,calibration,dirichlet,multiclass,probability
Platform: UNKNOWN
Classifier: Programming Language :: Python :: 3
Classifier: License :: OSI Approved :: MIT License
Classifier: Operating System :: OS Independent
Requires-Python: >=3.6
Requires-Dist: numpy (<0.19.2jaxjaxlibautograd,<1.0.1scikit-learn>=0.19.1,<1.14.3scipy>=1.0.0,>=1.14.2)
